trngen/__init__.py
trngen/core.py
trngen/entropies/__init__.py
trngen/entropies/audio.py
trngen/entropies/cursor.py
trngen/entropies/disk.py
trngen/entropies/display.py
trngen/entropies/network.py
trngen/entropies/timer.py
trngen/utils/csv_rw.py
trngen/utils/entropy_enhancer.py
TRNGen-0.0.2.dist-info/LICENSE
TRNGen-0.0.2.dist-info/METADATA
TRNGen-0.0.2.dist-info/WHEEL
TRNGen-0.0.2.dist-info/top_level.txt
TRNGen-0.0.2.dist-info/RECORD
