Metadata-Version: 2.1
Name: TRNGen
Version: 0.0.2
Summary: Truly Random Number Generator
Author-email: Flori Batusha <floribatusha0@gmail.com>
Project-URL: Check Github, https://github.com/riflosnake/TRNGen
Classifier: Programming Language :: Python :: 3
Classifier: License :: OSI Approved :: MIT License
Classifier: Operating System :: OS Independent
Requires-Python: >=3.7
License-File: LICENSE
Requires-Dist: pyautogui >=0.9.54
Requires-Dist: psutil >=5.9.6
Requires-Dist: sounddevice >=0.4.6
